aleksis/apps/alsijil/__init__.py
aleksis/apps/alsijil/apps.py
aleksis/apps/alsijil/checks.py
aleksis/apps/alsijil/forms.py
aleksis/apps/alsijil/frontend/components/coursebook/Coursebook.vue
aleksis/apps/alsijil/frontend/components/coursebook/CoursebookControls.vue
aleksis/apps/alsijil/frontend/components/coursebook/CoursebookLoader.vue
aleksis/apps/alsijil/frontend/components/coursebook/CoursebookPrintDialog.vue
aleksis/apps/alsijil/frontend/components/coursebook/absences/AbsenceCreationDialog.vue
aleksis/apps/alsijil/frontend/components/coursebook/absences/AbsenceCreationForm.vue
aleksis/apps/alsijil/frontend/components/coursebook/absences/AbsenceCreationSummary.vue
aleksis/apps/alsijil/frontend/components/coursebook/absences/DocumentationAbsences.vue
aleksis/apps/alsijil/frontend/components/coursebook/absences/DocumentationAbsencesModal.vue
aleksis/apps/alsijil/frontend/components/coursebook/absences/ManageStudentsDialog.vue
aleksis/apps/alsijil/frontend/components/coursebook/absences/ManageStudentsTrigger.vue
aleksis/apps/alsijil/frontend/components/coursebook/absences/ParticipationList.vue
aleksis/apps/alsijil/frontend/components/coursebook/absences/TardinessChip.vue
aleksis/apps/alsijil/frontend/components/coursebook/absences/TardinessField.vue
aleksis/apps/alsijil/frontend/components/coursebook/absences/UpdateParticipation.vue
aleksis/apps/alsijil/frontend/components/coursebook/absences/UpdateParticipations.vue
aleksis/apps/alsijil/frontend/components/coursebook/absences/absenceCreation.graphql
aleksis/apps/alsijil/frontend/components/coursebook/absences/participationStatus.graphql
aleksis/apps/alsijil/frontend/components/coursebook/absences/selectParticipationMixin.js
aleksis/apps/alsijil/frontend/components/coursebook/absences/sendToServerMixin.js
aleksis/apps/alsijil/frontend/components/coursebook/absences/updateParticipationMixin.js
aleksis/apps/alsijil/frontend/components/coursebook/coursebook.graphql
aleksis_app_alsijil-4.0.0.dist-info/LICENCE.rst
aleksis_app_alsijil-4.0.0.dist-info/METADATA
aleksis_app_alsijil-4.0.0.dist-info/WHEEL
aleksis_app_alsijil-4.0.0.dist-info/entry_points.txt
aleksis_app_alsijil-4.0.0.dist-info/RECORD
